volare_signals/__init__.py
volare_signals/client.py
volare_signals/exceptions.py
volare_signals/models.py
volare_signals/retry.py
volare_signals-1.0.3.dist-info/METADATA
volare_signals-1.0.3.dist-info/WHEEL
volare_signals-1.0.3.dist-info/licenses/LICENSE
volare_signals-1.0.3.dist-info/RECORD
