Metadata-Version: 2.4
Name: volare-signals
Version: 1.0.3
Summary: Python client library for the Volare Signals API
Project-URL: Homepage, https://volaretrading.com
Project-URL: Documentation, https://docs.volaretrading.com/api/signals
Project-URL: Repository, https://github.com/volaretrading/volare-signals-python
Project-URL: Issues, https://github.com/volaretrading/volare-signals-python/issues
Project-URL: Changelog, https://github.com/volaretrading/volare-signals-python/blob/main/CHANGELOG.md
Author-email: Volare Trading <support@volaretrading.com>
License-Expression: MIT
License-File: LICENSE
Keywords: api,client,finance,signals,stocks,trading,volare
Classifier: Development Status :: 5 - Production/Stable
Classifier: Intended Audience :: Developers
Classifier: Intended Audience :: Financial and Insurance Industry
Classifier: License :: OSI Approved :: MIT License
Classifier: Operating System :: OS Independent
Classifier: Programming Language :: Python :: 3
Classifier: Programming Language :: Python :: 3.10
Classifier: Programming Language :: Python :: 3.11
Classifier: Programming Language :: Python :: 3.12
Classifier: Programming Language :: Python :: 3.13
Classifier: Topic :: Office/Business :: Financial :: Investment
Classifier: Topic :: Software Development :: Libraries :: Python Modules
Classifier: Typing :: Typed
Requires-Python: >=3.10
Requires-Dist: httpx>=0.25.0
Requires-Dist: pydantic>=2.0.0
Provides-Extra: dev
Requires-Dist: mypy>=1.8.0; extra == 'dev'
Requires-Dist: pre-commit>=3.6.0; extra == 'dev'
Requires-Dist: pytest-asyncio>=0.23.0; extra == 'dev'
Requires-Dist: pytest-cov>=4.0.0; extra == 'dev'
Requires-Dist: pytest>=8.0.0; extra == 'dev'
Requires-Dist: python-dotenv>=1.0.0; extra == 'dev'
Requires-Dist: ruff==0.9.0; extra == 'dev'
